azuremlcli/__init__.py
azuremlcli/__main__.py
azuremlcli/az_utils.py
azuremlcli/azuremlutilities.py
azuremlcli/batch_workflows.py
azuremlcli/batchutilities.py
azuremlcli/cli_util.py
azuremlcli/docker_utils.py
azuremlcli/k8s_utils.py
azuremlcli/realtimeutilities.py
azuremlcli/data/acstemplate.json
azuremlcli/data/acstemplateparameters.json
azuremlcli/data/appinsightstemplate.json
azuremlcli/data/appinsightstemplateparameters.json
azuremlcli/data/azureml-fe-dep.yaml
azuremlcli/data/azureml-fe-service.yaml
azuremlcli/data/batch_create_payload.json
azuremlcli/data/batch_job_definition.json
azuremlcli/data/example_app.py
azuremlcli/data/getsample.py
azuremlcli/data/kubernetes_deployment_template.yaml
azuremlcli/data/kubernetes_service_template.yaml
azuremlcli/data/marathon.json
azuremlcli/data/preamble
azuremlcli/data/sample.ps1
azuremlcli/data/sample.sh
azuremlcli/data/spark_batch_deployment.yaml
azuremlcli/data/spark_batch_service.json
azuremlcli/data/testrequest.json
azuremlcli-0.2rc427.data/scripts/aml
azuremlcli-0.2rc427.data/scripts/aml.bat
azuremlcli-0.2rc427.dist-info/DESCRIPTION.rst
azuremlcli-0.2rc427.dist-info/METADATA
azuremlcli-0.2rc427.dist-info/RECORD
azuremlcli-0.2rc427.dist-info/WHEEL
azuremlcli-0.2rc427.dist-info/metadata.json
azuremlcli-0.2rc427.dist-info/top_level.txt
