Metadata-Version: 2.0
Name: azuremlcli
Version: 0.2rc427
Summary: Microsoft Azure Machine Learning Command Line Tools
Home-page: https://github.com/Azure/amlbdcli
Author: Microsoft
Author-email: deployml@microsoft.com
License: MIT
Platform: UNKNOWN
Classifier: Development Status :: 3 - Alpha
Classifier: Intended Audience :: Developers
Classifier: Intended Audience :: System Administrators
Classifier: License :: OSI Approved :: MIT License
Classifier: Programming Language :: Python :: 2.7
Classifier: Programming Language :: Python :: 3.5
Requires-Dist: azure-cli (>=0.1.0b11)
Requires-Dist: azure-storage (>=0.33)
Requires-Dist: future
Requires-Dist: kubernetes (>=1.0.0)
Requires-Dist: pyyaml (>=3.12)
Requires-Dist: tabulate (>=0.7.7)
